fantable/__init__.py
fantable/fandatab.py
fantable-1.6.dist-info/LICENSE.txt
fantable-1.6.dist-info/METADATA
fantable-1.6.dist-info/WHEEL
fantable-1.6.dist-info/top_level.txt
fantable-1.6.dist-info/RECORD
