Metadata-Version: 2.1
Name: fantable
Version: 1.6
Summary: Table Builder For Python
Home-page: https://github.com/sptty-chan/fantable
Author: Sptty Chan
Author-email: sptty_chan@ccmail.uk
License: MIT
Platform: UNKNOWN
Classifier: Development Status :: 3 - Alpha
Classifier: Intended Audience :: Developers
Classifier: Topic :: Software Development :: Build Tools
Classifier: License :: OSI Approved :: MIT License
Classifier: Programming Language :: Python :: 3
Classifier: Programming Language :: Python :: 3.4
Classifier: Programming Language :: Python :: 3.5
Classifier: Programming Language :: Python :: 3.6
Classifier: Programming Language :: Python :: 3.10
License-File: LICENSE.txt
